Workbook

Sheet Simulador (2)
B2: Precio de Equipo | D2: 160
B3: Abono | D3: 0.3
B4: Ingreso mensual (USD) | D4: 800
B5: Monto a financiar (USD) | D5: =D2-D2*D3 -> 112
B7: Plazo (meses) | C7: Cuota Quincenal | D7: Cuota mensual | E7: Multiplo | F7: Total pagar cliente | G7: Límite 10% | H7: Viable 10% | I7: Límite 20% | J7: Viable 20% | K7: Límite 30% | L7: Viable 30%
B8: 4 | C8: =D8/2 -> 23.183259 | D8: =F8/B8 -> 46.366518 | E8: 1.6559471 | F8: =D5*E8 -> 185.46607 | G8: =D4*0.1 -> 80 | H8: =IF(D8<=G8,"SI","NO") -> SI | I8: =D4*0.2 -> 160 | J8: =IF(D8<=I8,"SI","NO") -> SI | K8: =D4*0.3 -> 240 | L8: =IF(D8<=K8,"SI","NO") -> SI
B9: 6 | C9: =D9/2 -> 16.444081 | D9: =F9/B9 -> 32.888161 | E9: 1.7618658 | F9: =D5*E9 -> 197.32897 | G9: =D4*0.1 -> 80 | H9: =IF(D9<=G9,"SI","NO") -> SI | I9: =D4*0.2 -> 160 | J9: =IF(D9<=I9,"SI","NO") -> SI | K9: =D4*0.3 -> 240 | L9: =IF(D9<=K9,"SI","NO") -> SI
B10: 8 | C10: =D10/2 -> 14.14 | D10: =F10/B10 -> 28.28 | E10: 2.02 | F10: =D5*E10 -> 226.24 | G10: =D4*0.1 -> 80 | H10: =IF(D10<=G10,"SI","NO") -> SI | I10: =D4*0.2 -> 160 | J10: =IF(D10<=I10,"SI","NO") -> SI | K10: =D4*0.3 -> 240 | L10: =IF(D10<=K10,"SI","NO") -> SI
D11: =D10*B10 -> 226.24 | E11: =D11/D5 -> 2.02 | F11: 226.51
B12: Instrucciones:
B13: - Cambia B1 (Ingreso) y B2 (Monto) para simular.
B14: - La cuota mensual se compara contra 10%, 20% y 30% del ingreso.
B15: - Las columnas Viable indican 'SI' (viable) o 'NO' (no viable).

Sheet Hoja1
A1: 0.45 * score_apc_norm +
A2: 0.20 * biometria_confianza +
A3: 0.20 * capacidad_norm + # (cuota_max - cuota)/cuota_max
A4: 0.10 * referencias_score + # validez/contactabilidad
A5: 0.10 * geocomportamiento # consistencia ubicación/dispositivo

Sheet Hoja3
O1: Meses | P1: Multiplos
B2: Salario | C2: 700 | O2: 4 | P2: 1.7 | U2: Tasa Efectiva | V2: =+IRR(X7:X23)*24 -> 2.7009429
B3: Equipo | C3: 350 | O3: 6 | P3: 1.8 | U3: Tasa Nominal | V3: =V2/12 -> 0.22507857
O4: 8 | P4: 2.2 | U4: Tasa Quincenal | V4: =V3/2 -> 0.11253929
U5: Amortizacion
D6: Motor de decision | G6: 8 | I6: Financiamiento Aprobado | M6: Detalle de Financiamiento | U6: Cuotas | V6: Interes | W6: capital | X6: Valor cuota | Y6: Saldo | AC6: 4 | AD6: 6 | AE6: 8 | AG6: 4 | AH6: 6 | AI6: 8
B7: Cortes | C7: Categorias | D7: Score Apc | E7: Endeudamiento | F7: Abonos | G7: Meses | I7: Cuota | J7: Meses | K7: Maximo a Financiar | M7: Equipo | N7: Abono | O7: Monto a financiar | P7: Multiplo | Q7: Financiamiento | R7: Cuotas quincenal | S7: Veredicto | X7: =+-(M8*(1-F8)) -> -280 | Y7: =O8 -> 280 | AB7: 1 | AC7: =R8 -> 38.5 | AD7: =R8 -> 38.5 | AE7: =R8 -> 38.5 | AG7: =O8 -> 280 | AH7: =AG7 -> 280 | AI7: =AH7 -> 280
B8: Tier A | C8: (Low Risk) | D8: 550+ | E8: 0.2 | F8: 0.2 | G8: 4,6,8 | I8: =$C$2*E8 -> 140 | J8: =$G$6 -> 8 | K8: =I8*J8 -> 1120 | M8: =C3 -> 350 | N8: =M8*F8 -> 70 | O8: =M8-N8 -> 280 | P8: =VLOOKUP(J8,O:P,2,0) -> 2.2 | Q8: =O8*P8 -> 616 | R8: =((M8*(1-F8))*P8)/($G$6*2) -> 38.5 | S8: =IF(Q8<=K8,"APLICA","NO APLICA") -> APLICA | U8: 1 | V8: =Y7*$V$4 -> 31.511 | W8: =X8-V8 -> 6.989 | X8: {=INDEX(AC7:AE22,ROW($AC$1),MATCH($G$6,$AC$6:$AE$6,0))} -> 38.5 | Y8: =Y7-W8 -> 273.011 | AB8: 2 | AC8: =AC7 -> 38.5 | AD8: =AD7 -> 38.5 | AE8: =AE7 -> 38.5 | AG8: =AG7 -> 280 | AH8: =AH7 -> 280 | AI8: =AI7 -> 280
B9: Tier B | C9: (medio) | D9: 500-549 | E9: 0.15 | F9: 0.25 | G9: 4,6,8 | I9: =$C$2*E9 -> 105 | J9: =$G$6 -> 8 | K9: =I9*J9 -> 840 | M9: =M8 -> 350 | N9: =M9*F9 -> 87.5 | O9: =M9-N9 -> 262.5 | P9: =VLOOKUP(J9,O:P,2,0) -> 2.2 | Q9: =O9*P9 -> 577.5 | R9: =((M9*(1-F9))*P9)/($G$6*2) -> 36.09375 | S9: =IF(Q9<=K9,"APLICA","NO APLICA") -> APLICA | U9: 2 | V9: =Y8*$V$4 -> 30.724463 | W9: =X9-V9 -> 7.775537 | X9: {=INDEX(AC8:AE23,ROW($AC$1),MATCH($G$6,$AC$6:$AE$6,0))} -> 38.5 | Y9: =Y8-W9 -> 265.23546 | AB9: 3 | AC9: =AC8 -> 38.5 | AD9: =AD8 -> 38.5 | AE9: =AE8 -> 38.5 | AG9: =AG8 -> 280 | AH9: =AH8 -> 280 | AI9: =AI8 -> 280
B10: Tier C | C10: (alto) | D10: 450-499 | E10: 0.1 | F10: 0.3 | G10: 4,6,8 | I10: =$C$2*E10 -> 70 | J10: =$G$6 -> 8 | K10: =I10*J10 -> 560 | M10: =M9 -> 350 | N10: =M10*F10 -> 105 | O10: =M10-N10 -> 245 | P10: =VLOOKUP(J10,O:P,2,0) -> 2.2 | Q10: =O10*P10 -> 539 | R10: =((M10*(1-F10))*P10)/($G$6*2) -> 33.6875 | S10: =IF(Q10<=K10,"APLICA","NO APLICA") -> APLICA | U10: 3 | V10: =Y9*$V$4 -> 29.84941 | W10: =X10-V10 -> 8.6505904 | X10: {=INDEX(AC9:AE24,ROW($AC$1),MATCH($G$6,$AC$6:$AE$6,0))} -> 38.5 | Y10: =Y9-W10 -> 256.58487 | AB10: 4 | AC10: =AC9 -> 38.5 | AD10: =AD9 -> 38.5 | AE10: =AE9 -> 38.5 | AG10: =AG9 -> 280 | AH10: =AH9 -> 280 | AI10: =AI9 -> 280
B11: Tier D | C11: (Very High) | D11: -450 | E11: Reject | F11: Rejected | G11: Rejected | I11: Rejected | J11: Rejected | K11: Rejected | M11: =M10 -> 350 | N11: Rejected | O11: Rejected | P11: Rejected | Q11: Rejected | R11: Rejected | S11: Rejected | U11: 4 | V11: =Y10*$V$4 -> 28.875878 | W11: =X11-V11 -> 9.6241217 | X11: {=INDEX(AC10:AE25,ROW($AC$1),MATCH($G$6,$AC$6:$AE$6,0))} -> 38.5 | Y11: =Y10-W11 -> 246.96075 | AB11: 5 | AC11: =AC10 -> 38.5 | AD11: =AD10 -> 38.5 | AE11: =AE10 -> 38.5 | AG11: =AG10 -> 280 | AH11: =AH10 -> 280 | AI11: =AI10 -> 280
B12: Tier E | C12: (No Score) | D12: Salario | E12: 0.15 | F12: 0.25 | G12: 4,6,8 | I12: =$C$2*E12 -> 105 | J12: =$G$6 -> 8 | K12: =I12*J12 -> 840 | M12: =M11 -> 350 | N12: =M12*F12 -> 87.5 | O12: =M12-N12 -> 262.5 | P12: =VLOOKUP(J12,O:P,2,0) -> 2.2 | Q12: =O12*P12 -> 577.5 | R12: =((M12*(1-F12))*P12)/($G$6*2) -> 36.09375 | S12: =IF(Q12<=K12,"APLICA","NO APLICA") -> APLICA | U12: 5 | V12: =Y11*$V$4 -> 27.792787 | W12: =X12-V12 -> 10.707213 | X12: {=INDEX(AC11:AE26,ROW($AC$1),MATCH($G$6,$AC$6:$AE$6,0))} -> 38.5 | Y12: =Y11-W12 -> 236.25354 | AB12: 6 | AC12: =AC11 -> 38.5 | AD12: =AD11 -> 38.5 | AE12: =AE11 -> 38.5 | AG12: =AG11 -> 280 | AH12: =AH11 -> 280 | AI12: =AI11 -> 280
B13: Tier F | C13: (No Salario) | D13: 600+ | E13: 0.15 | F13: 0.25 | G13: 4,6,8 | I13: =$C$2*E13 -> 105 | J13: =$G$6 -> 8 | K13: =I13*J13 -> 840 | M13: =M12 -> 350 | N13: =M13*F13 -> 87.5 | O13: =M13-N13 -> 262.5 | P13: =VLOOKUP(J13,O:P,2,0) -> 2.2 | Q13: =O13*P13 -> 577.5 | R13: =((M13*(1-F13))*P13)/($G$6*2) -> 36.09375 | S13: =IF(Q13<=K13,"APLICA","NO APLICA") -> APLICA | U13: 6 | V13: =Y12*$V$4 -> 26.587804 | W13: =X13-V13 -> 11.912196 | X13: {=INDEX(AC12:AE27,ROW($AC$1),MATCH($G$6,$AC$6:$AE$6,0))} -> 38.5 | Y13: =Y12-W13 -> 224.34134 | AB13: 7 | AC13: =AC12 -> 38.5 | AD13: =AD12 -> 38.5 | AE13: =AE12 -> 38.5 | AG13: =AG12 -> 280 | AH13: =AH12 -> 280 | AI13: =AI12 -> 280
B14: Tier G | C14: (Sin Referencia) | D14: 0 | E14: Reject | F14: Rejected | G14: Rejected | I14: Rejected | J14: Rejected | K14: Rejected | M14: Rejected | N14: Rejected | O14: Rejected | P14: Rejected | Q14: Rejected | R14: Rejected | S14: Rejected | U14: 7 | V14: =Y13*$V$4 -> 25.247214 | W14: =X14-V14 -> 13.252786 | X14: {=INDEX(AC13:AE28,ROW($AC$1),MATCH($G$6,$AC$6:$AE$6,0))} -> 38.5 | Y14: =Y13-W14 -> 211.08856 | AB14: 8 | AC14: =AC13 -> 38.5 | AD14: =AD13 -> 38.5 | AE14: =AE13 -> 38.5 | AG14: =AG13 -> 280 | AH14: =AH13 -> 280 | AI14: =AI13 -> 280
B15: Tier H | C15: Cliente Activo | D15: 0 | E15: Reject | F15: Rejected | G15: Rejected | I15: Rejected | J15: Rejected | K15: Rejected | M15: Rejected | N15: Rejected | O15: Rejected | P15: Rejected | Q15: Rejected | R15: Rejected | S15: Rejected | U15: 8 | V15: =Y14*$V$4 -> 23.755755 | W15: =X15-V15 -> 14.744245 | X15: {=INDEX(AC14:AE29,ROW($AC$1),MATCH($G$6,$AC$6:$AE$6,0))} -> 38.5 | Y15: =Y14-W15 -> 196.34431 | AB15: 9 | AD15: =AD14 -> 38.5 | AE15: =AE14 -> 38.5 | AH15: =AH14 -> 280 | AI15: =AI14 -> 280
U16: 9 | V16: =Y15*$V$4 -> 22.096449 | W16: =X16-V16 -> 16.403551 | X16: {=INDEX(AC15:AE30,ROW($AC$1),MATCH($G$6,$AC$6:$AE$6,0))} -> 38.5 | Y16: =Y15-W16 -> 179.94076 | AB16: 10 | AD16: =AD15 -> 38.5 | AE16: =AE15 -> 38.5 | AH16: =AH15 -> 280 | AI16: =AI15 -> 280
U17: 10 | V17: =Y16*$V$4 -> 20.250405 | W17: =X17-V17 -> 18.249595 | X17: {=INDEX(AC16:AE31,ROW($AC$1),MATCH($G$6,$AC$6:$AE$6,0))} -> 38.5 | Y17: =Y16-W17 -> 161.69116 | AB17: 11 | AD17: =AD16 -> 38.5 | AE17: =AE16 -> 38.5 | AH17: =AH16 -> 280 | AI17: =AI16 -> 280
U18: 11 | V18: =Y17*$V$4 -> 18.196608 | W18: =X18-V18 -> 20.303392 | X18: {=INDEX(AC17:AE32,ROW($AC$1),MATCH($G$6,$AC$6:$AE$6,0))} -> 38.5 | Y18: =Y17-W18 -> 141.38777 | AB18: 12 | AD18: =AD17 -> 38.5 | AE18: =AE17 -> 38.5 | AH18: =AH17 -> 280 | AI18: =AI17 -> 280
U19: 12 | V19: =Y18*$V$4 -> 15.911679 | W19: =X19-V19 -> 22.588321 | X19: {=INDEX(AC18:AE33,ROW($AC$1),MATCH($G$6,$AC$6:$AE$6,0))} -> 38.5 | Y19: =Y18-W19 -> 118.79945 | AB19: 13 | AE19: =AE18 -> 38.5 | AI19: =AI18 -> 280
U20: 13 | V20: =Y19*$V$4 -> 13.369605 | W20: =X20-V20 -> 25.130395 | X20: {=INDEX(AC19:AE34,ROW($AC$1),MATCH($G$6,$AC$6:$AE$6,0))} -> 38.5 | Y20: =Y19-W20 -> 93.669057 | AB20: 14 | AE20: =AE19 -> 38.5 | AI20: =AI19 -> 280
U21: 14 | V21: =Y20*$V$4 -> 10.541449 | W21: =X21-V21 -> 27.958551 | X21: {=INDEX(AC20:AE35,ROW($AC$1),MATCH($G$6,$AC$6:$AE$6,0))} -> 38.5 | Y21: =Y20-W21 -> 65.710506 | AB21: 15 | AE21: =AE20 -> 38.5 | AI21: =AI20 -> 280
U22: 15 | V22: =Y21*$V$4 -> 7.3950134 | W22: =X22-V22 -> 31.104987 | X22: {=INDEX(AC21:AE36,ROW($AC$1),MATCH($G$6,$AC$6:$AE$6,0))} -> 38.5 | Y22: =Y21-W22 -> 34.605519 | AB22: 16 | AE22: =AE21 -> 38.5 | AI22: =AI21 -> 280
U23: 16 | V23: =Y22*$V$4 -> 3.8944804 | W23: =X23-V23 -> 34.60552 | X23: {=INDEX(AC22:AE37,ROW($AC$1),MATCH($G$6,$AC$6:$AE$6,0))} -> 38.5 | Y23: =Y22-W23 -> -8.1712201e-08
U24: Total | V24: =SUM(V8:V23) -> 336 | W24: =SUM(W8:W23) -> 280 | X24: =V24+W24 -> 616

Sheet Simulador
A1: Precio de Equipo | D1: 400
A2: Abono | D2: 0.2
A3: Abono $ | D3: =D1*D2 -> 80
A4: Ingreso mensual (USD) | D4: 400
A5: Monto a financiar (USD) | D5: =+D1-D3 -> 320
A6: Total a pagar cliente (USD) | D6: =D1-D3 -> 320
A8: Plazo (meses) | B8: Multiplo | C8: Cuota Quincenal | D8: Cuota mensual | E8: Límite 10% | F8: Viable 10% | G8: Límite 20% | H8: Viable 20% | I8: Límite 30% | J8: Viable 30%
A9: 4 | B9: 1.6559471 | C9: =D9/2 -> 40 | D9: =D5/A9 -> 80 | E9: =D4*0.1 -> 40 | F9: =IF(D9<=E9,"SI","NO") -> NO | G9: =D4*0.2 -> 80 | H9: =IF(D9<=G9,"SI","NO") -> SI | I9: =D4*0.3 -> 120 | J9: =IF(D9<=I9,"SI","NO") -> SI
A10: 6 | B10: 1.7618658 | C10: =D10/2 -> 26.666667 | D10: =D5/A10 -> 53.333333 | E10: =D4*0.1 -> 40 | F10: =IF(D10<=E10,"SI","NO") -> NO | G10: =D4*0.2 -> 80 | H10: =IF(D10<=G10,"SI","NO") -> SI | I10: =D4*0.3 -> 120 | J10: =IF(D10<=I10,"SI","NO") -> SI
A11: 8 | B11: 2.0194294 | C11: =D11/2 -> 20 | D11: =D5/A11 -> 40 | E11: =D4*0.1 -> 40 | F11: =IF(D11<=E11,"SI","NO") -> SI | G11: =D4*0.2 -> 80 | H11: =IF(D11<=G11,"SI","NO") -> SI | I11: =D4*0.3 -> 120 | J11: =IF(D11<=I11,"SI","NO") -> SI
A13: Instrucciones:
A14: - Cambia B1 (Ingreso) y B2 (Monto) para simular.
A15: - La cuota mensual se compara contra 10%, 20% y 30% del ingreso.
A16: - Las columnas Viable indican 'SI' (viable) o 'NO' (no viable).

Sheet Tabla Rápida
A1: Ingreso mensual (USD) | B1: Monto (desde Simulador B2)
B2: =Simulador!D5 -> 320
A4: Ingreso | B4: Cuota 4m | C4: Viable 10% (4m) | D4: Viable 20% (4m) | E4: Viable 30% (4m) | F4: Cuota 6m | G4: Viable 10% (6m) | H4: Viable 20% (6m) | I4: Viable 30% (6m) | J4: Cuota 8m | K4: Viable 10% (8m) | L4: Viable 20% (8m) | M4: Viable 30% (8m)
A5: 400 | B5: =Simulador!D5/4 -> 80 | C5: =IF(B5<=A5*0.1,"SI","NO") -> NO | D5: =IF(B5<=A5*0.2,"SI","NO") -> SI | E5: =IF(B5<=A5*0.3,"SI","NO") -> SI | F5: =Simulador!D5/6 -> 53.333333 | G5: =IF(F5<=A5*0.1,"SI","NO") -> NO | H5: =IF(F5<=A5*0.2,"SI","NO") -> SI | I5: =IF(F5<=A5*0.3,"SI","NO") -> SI | J5: =Simulador!D5/8 -> 40 | K5: =IF(J5<=A5*0.1,"SI","NO") -> SI | L5: =IF(J5<=A5*0.2,"SI","NO") -> SI | M5: =IF(J5<=A5*0.3,"SI","NO") -> SI
A6: 500 | B6: =Simulador!D5/4 -> 80 | C6: =IF(B6<=A6*0.1,"SI","NO") -> NO | D6: =IF(B6<=A6*0.2,"SI","NO") -> SI | E6: =IF(B6<=A6*0.3,"SI","NO") -> SI | F6: =Simulador!D5/6 -> 53.333333 | G6: =IF(F6<=A6*0.1,"SI","NO") -> NO | H6: =IF(F6<=A6*0.2,"SI","NO") -> SI | I6: =IF(F6<=A6*0.3,"SI","NO") -> SI | J6: =Simulador!D5/8 -> 40 | K6: =IF(J6<=A6*0.1,"SI","NO") -> SI | L6: =IF(J6<=A6*0.2,"SI","NO") -> SI | M6: =IF(J6<=A6*0.3,"SI","NO") -> SI
A7: 600 | B7: =Simulador!D5/4 -> 80 | C7: =IF(B7<=A7*0.1,"SI","NO") -> NO | D7: =IF(B7<=A7*0.2,"SI","NO") -> SI | E7: =IF(B7<=A7*0.3,"SI","NO") -> SI | F7: =Simulador!D5/6 -> 53.333333 | G7: =IF(F7<=A7*0.1,"SI","NO") -> SI | H7: =IF(F7<=A7*0.2,"SI","NO") -> SI | I7: =IF(F7<=A7*0.3,"SI","NO") -> SI | J7: =Simulador!D5/8 -> 40 | K7: =IF(J7<=A7*0.1,"SI","NO") -> SI | L7: =IF(J7<=A7*0.2,"SI","NO") -> SI | M7: =IF(J7<=A7*0.3,"SI","NO") -> SI
A8: 700 | B8: =Simulador!D5/4 -> 80 | C8: =IF(B8<=A8*0.1,"SI","NO") -> NO | D8: =IF(B8<=A8*0.2,"SI","NO") -> SI | E8: =IF(B8<=A8*0.3,"SI","NO") -> SI | F8: =Simulador!D5/6 -> 53.333333 | G8: =IF(F8<=A8*0.1,"SI","NO") -> SI | H8: =IF(F8<=A8*0.2,"SI","NO") -> SI | I8: =IF(F8<=A8*0.3,"SI","NO") -> SI | J8: =Simulador!D5/8 -> 40 | K8: =IF(J8<=A8*0.1,"SI","NO") -> SI | L8: =IF(J8<=A8*0.2,"SI","NO") -> SI | M8: =IF(J8<=A8*0.3,"SI","NO") -> SI
A9: 800 | B9: =Simulador!D5/4 -> 80 | C9: =IF(B9<=A9*0.1,"SI","NO") -> SI | D9: =IF(B9<=A9*0.2,"SI","NO") -> SI | E9: =IF(B9<=A9*0.3,"SI","NO") -> SI | F9: =Simulador!D5/6 -> 53.333333 | G9: =IF(F9<=A9*0.1,"SI","NO") -> SI | H9: =IF(F9<=A9*0.2,"SI","NO") -> SI | I9: =IF(F9<=A9*0.3,"SI","NO") -> SI | J9: =Simulador!D5/8 -> 40 | K9: =IF(J9<=A9*0.1,"SI","NO") -> SI | L9: =IF(J9<=A9*0.2,"SI","NO") -> SI | M9: =IF(J9<=A9*0.3,"SI","NO") -> SI
A10: 1000 | B10: =Simulador!D5/4 -> 80 | C10: =IF(B10<=A10*0.1,"SI","NO") -> SI | D10: =IF(B10<=A10*0.2,"SI","NO") -> SI | E10: =IF(B10<=A10*0.3,"SI","NO") -> SI | F10: =Simulador!D5/6 -> 53.333333 | G10: =IF(F10<=A10*0.1,"SI","NO") -> SI | H10: =IF(F10<=A10*0.2,"SI","NO") -> SI | I10: =IF(F10<=A10*0.3,"SI","NO") -> SI | J10: =Simulador!D5/8 -> 40 | K10: =IF(J10<=A10*0.1,"SI","NO") -> SI | L10: =IF(J10<=A10*0.2,"SI","NO") -> SI | M10: =IF(J10<=A10*0.3,"SI","NO") -> SI
A11: 1500 | B11: =Simulador!D5/4 -> 80 | C11: =IF(B11<=A11*0.1,"SI","NO") -> SI | D11: =IF(B11<=A11*0.2,"SI","NO") -> SI | E11: =IF(B11<=A11*0.3,"SI","NO") -> SI | F11: =Simulador!D5/6 -> 53.333333 | G11: =IF(F11<=A11*0.1,"SI","NO") -> SI | H11: =IF(F11<=A11*0.2,"SI","NO") -> SI | I11: =IF(F11<=A11*0.3,"SI","NO") -> SI | J11: =Simulador!D5/8 -> 40 | K11: =IF(J11<=A11*0.1,"SI","NO") -> SI | L11: =IF(J11<=A11*0.2,"SI","NO") -> SI | M11: =IF(J11<=A11*0.3,"SI","NO") -> SI
A12: 2000 | B12: =Simulador!D5/4 -> 80 | C12: =IF(B12<=A12*0.1,"SI","NO") -> SI | D12: =IF(B12<=A12*0.2,"SI","NO") -> SI | E12: =IF(B12<=A12*0.3,"SI","NO") -> SI | F12: =Simulador!D5/6 -> 53.333333 | G12: =IF(F12<=A12*0.1,"SI","NO") -> SI | H12: =IF(F12<=A12*0.2,"SI","NO") -> SI | I12: =IF(F12<=A12*0.3,"SI","NO") -> SI | J12: =Simulador!D5/8 -> 40 | K12: =IF(J12<=A12*0.1,"SI","NO") -> SI | L12: =IF(J12<=A12*0.2,"SI","NO") -> SI | M12: =IF(J12<=A12*0.3,"SI","NO") -> SI
A13: 3000 | B13: =Simulador!D5/4 -> 80 | C13: =IF(B13<=A13*0.1,"SI","NO") -> SI | D13: =IF(B13<=A13*0.2,"SI","NO") -> SI | E13: =IF(B13<=A13*0.3,"SI","NO") -> SI | F13: =Simulador!D5/6 -> 53.333333 | G13: =IF(F13<=A13*0.1,"SI","NO") -> SI | H13: =IF(F13<=A13*0.2,"SI","NO") -> SI | I13: =IF(F13<=A13*0.3,"SI","NO") -> SI | J13: =Simulador!D5/8 -> 40 | K13: =IF(J13<=A13*0.1,"SI","NO") -> SI | L13: =IF(J13<=A13*0.2,"SI","NO") -> SI | M13: =IF(J13<=A13*0.3,"SI","NO") -> SI

Sheet Hoja2
B2: 5
B3: 1 | C3: 2 | D3: 3 | E3: 4 | F3: 5 | G3: 6 | H3: 7 | I3: 8 | J3: 9 | K3: 10 | L3: 11 | M3: 12
B4: 500 | C4: 500 | D4: 500 | E4: 1000 | F4: 1000 | G4: 1000 | H4: 2000 | I4: 2000 | J4: 2000 | K4: 2000 | L4: 2000 | M4: 2000
B5: =B4*$B$2 -> 2500 | C5: =C4*$B$2 -> 2500 | D5: =D4*$B$2 -> 2500 | E5: =E4*$B$2 -> 5000 | F5: =F4*$B$2 -> 5000 | G5: =G4*$B$2 -> 5000 | H5: =H4*$B$2 -> 10000 | I5: =I4*$B$2 -> 10000 | ... M5: =M4*$B$2 -> 10000
